kwasa/__init__.py
kwasa/checks.py
kwasa/main.py
kwasa/functions/__init__.py
kwasa/functions/_clone.py
kwasa/functions/_update.py
kwasa/functions/main.py
kwasa/libs/__init__.py
kwasa/libs/delete_repos.py
kwasa/libs/exceptions.py
kwasa/libs/helper.py
kwasa/libs/permissions.py
kwasa/logger/__init__.py
kwasa/logger/color.py
kwasa/logger/format.py
kwasa/logger/log.py
kwasa_cli-1.0.1.dist-info/METADATA
kwasa_cli-1.0.1.dist-info/WHEEL
kwasa_cli-1.0.1.dist-info/entry_points.txt
kwasa_cli-1.0.1.dist-info/RECORD
