Metadata-Version: 2.4
Name: kwasa-cli
Version: 1.0.1
Summary: Simple CLI tool for cloning and updating the git repositories
Project-URL: Homepage, https://github.com/jeckonia49/kwasa-cli
Project-URL: Issues, https://github.com/jeckonia49/kwasa-cli/issues
Author-email: Jeckonia Kwasa <jeckonia@example.com>
License-Expression: MIT
Classifier: Programming Language :: Python :: 3
Classifier: Programming Language :: Python :: 3.13
Requires-Python: >=3.13
Requires-Dist: build>=1.2.2.post1
Requires-Dist: colored>=2.3.0
Requires-Dist: hatch>=1.14.0
Requires-Dist: mypy>=1.15.0
Requires-Dist: pre-commit>=4.2.0
Requires-Dist: pytest-cov>=6.1.1
Requires-Dist: pytest>=8.3.5
Requires-Dist: python-dotenv>=1.1.0
Requires-Dist: requests>=2.32.3
Requires-Dist: ruff>=0.11.4
Requires-Dist: setuptools>=78.1.0
Requires-Dist: twine>=6.1.0
Requires-Dist: types-requests>=2.32.0.20250328
Provides-Extra: dev
Requires-Dist: colored>=2.3.0; extra == 'dev'
Requires-Dist: mypy>=1.15.0; extra == 'dev'
Requires-Dist: pre-commit>=4.2.0; extra == 'dev'
Requires-Dist: pytest-cov>=6.1.1; extra == 'dev'
Requires-Dist: pytest>=8.3.5; extra == 'dev'
Requires-Dist: ruff>=0.11.4; extra == 'dev'
